chem_analysis/__init__.py
chem_analysis/config.py
chem_analysis/analysis/__init__.py
chem_analysis/analysis/peak.py
chem_analysis/analysis/peak_result.py
chem_analysis/analysis/change_detection/__init__.py
chem_analysis/analysis/change_detection/change_detection.py
chem_analysis/analysis/integration/__init__.py
chem_analysis/analysis/integration/bound_detection_criteria.py
chem_analysis/analysis/integration/bound_detection_derivative.py
chem_analysis/analysis/integration/bound_detection_distribution_fitting.py
chem_analysis/analysis/integration/bound_detection_fwhm.py
chem_analysis/analysis/integration/bound_detection_parabola.py
chem_analysis/analysis/integration/boundary_detection.py
chem_analysis/analysis/integration/integrate_signal.py
chem_analysis/analysis/integration/intregrate_signal2D.py
chem_analysis/analysis/integration/result_integration.py
chem_analysis/analysis/integration/sec_peak.py
chem_analysis/analysis/line_fitting/__init__.py
chem_analysis/analysis/line_fitting/fitting.py
chem_analysis/analysis/line_fitting/gaussian_mixture.py
chem_analysis/analysis/line_fitting/peak_models.py
chem_analysis/analysis/ms_analysis/__init__.py
chem_analysis/analysis/ms_analysis/ms_similarity.py
chem_analysis/analysis/ms_analysis/picking_library.py
chem_analysis/analysis/ms_analysis/result_search.py
chem_analysis/analysis/ms_analysis/search_by_criteria.py
chem_analysis/analysis/ms_analysis/search_by_ms.py
chem_analysis/analysis/ms_analysis/search_by_time.py
chem_analysis/analysis/ms_extraction/__init__.py
chem_analysis/analysis/ms_extraction/baseline_subtraction.py
chem_analysis/analysis/ms_extraction/deconvolution.py
chem_analysis/analysis/ms_extraction/simple.py
chem_analysis/analysis/multi_component_analysis/__init__.py
chem_analysis/analysis/multi_component_analysis/constraints.py
chem_analysis/analysis/multi_component_analysis/metrics.py
chem_analysis/analysis/multi_component_analysis/muti_component_analysis.py
chem_analysis-0.0.7.dist-info/LICENSE.txt
chem_analysis-0.0.7.dist-info/METADATA
chem_analysis-0.0.7.dist-info/WHEEL
chem_analysis-0.0.7.dist-info/top_level.txt
chem_analysis-0.0.7.dist-info/RECORD
