Metadata-Version: 2.1
Name: chem_analysis
Version: 0.0.7
Summary: Analyzing experimental chemistry data
Home-page: https://github.com/dylanwal/chem_analysis
Author: Dylan Walsh
License: BSD
Keywords: materials characterization,materials science,baseline,background,baseline correction,baseline subtraction,chemistry,spectroscopy,NMR,IR,UV-VIS,GC,LC,UPLC,HPLC,GC-MS,MS,GPC,SEC,gas chromatography,mass spectrometry,nuclear magnetic resonance,size exclusion chromatography,gel permeation chromatography
Platform: any
Classifier: License :: OSI Approved :: BSD License
Classifier: Programming Language :: Python :: 3
Classifier: Programming Language :: Python :: 3 :: Only
Classifier: Programming Language :: Python :: 3.10
Classifier: Topic :: Scientific/Engineering
Classifier: Topic :: Scientific/Engineering :: Chemistry
Classifier: Topic :: Scientific/Engineering :: Information Analysis
Requires-Python: >=3.10
License-File: LICENSE.txt
Requires-Dist: numpy>=1.22.1
Requires-Dist: scipy>=1.7.3
Requires-Dist: tabulate>=0.9.0
Requires-Dist: bigsmiles>=0.0.10
Requires-Dist: rapidfuzz>=3.9.3
Provides-Extra: testing
Requires-Dist: pytest>=6.0; extra == "testing"
Requires-Dist: pytest-cov>=2.0; extra == "testing"
Requires-Dist: mypy>=0.910; extra == "testing"
Requires-Dist: flake8>=3.9; extra == "testing"
